malevich_space/__init__.py
malevich_space/ci/__init__.py
malevich_space/ci/manager.py
malevich_space/ci/platform.py
malevich_space/ci/report.py
malevich_space/ci/status.py
malevich_space/cli/__init__.py
malevich_space/cli/cli.py
malevich_space/cli/commands/__init__.py
malevich_space/cli/commands/asset.py
malevich_space/cli/commands/ci.py
malevich_space/cli/commands/component.py
malevich_space/cli/commands/env.py
malevich_space/cli/commands/schema.py
malevich_space/cli/commands/team.py
malevich_space/constants.py
malevich_space/gql/__init__.py
malevich_space/gql/api_key/__init__.py
malevich_space/gql/api_key/get_api_key_by_name.py
malevich_space/gql/asset/__init__.py
malevich_space/gql/asset/create.py
malevich_space/gql/asset/create_in_version.py
malevich_space/gql/asset/get.py
malevich_space/gql/cfg/__init__.py
malevich_space/gql/cfg/cfg.py
malevich_space/gql/cfg/set_in_flow_component_cfg.py
malevich_space/gql/collection/__init__.py
malevich_space/gql/collection/ca_comp.py
malevich_space/gql/collection/ca_in_flow.py
malevich_space/gql/collection/collection_alias.py
malevich_space/gql/collection/update_ca.py
malevich_space/gql/component/__init__.py
malevich_space/gql/component/add_app_to_comp_flow.py
malevich_space/gql/component/add_ca_to_comp_flow.py
malevich_space/gql/component/add_cfg_2_av_app.py
malevich_space/gql/component/add_comp_in_flow.py
malevich_space/gql/component/add_comp_to_org.py
malevich_space/gql/component/add_dep_2_op.py
malevich_space/gql/component/add_op_to_av.py
malevich_space/gql/component/add_tag.py
malevich_space/gql/component/app_comp.py
malevich_space/gql/component/attach_tag_to_comp.py
malevich_space/gql/component/autolayout.py
malevich_space/gql/component/branch.py
malevich_space/gql/component/component.py
malevich_space/gql/component/create_op.py
malevich_space/gql/component/flow_by_version_id.py
malevich_space/gql/component/flow_comp.py
malevich_space/gql/component/get_available_flows.py
malevich_space-0.5.0.dist-info/LICENSE
malevich_space-0.5.0.dist-info/METADATA
malevich_space-0.5.0.dist-info/WHEEL
malevich_space-0.5.0.dist-info/entry_points.txt
malevich_space-0.5.0.dist-info/RECORD
