Metadata-Version: 2.1
Name: malevich-space
Version: 0.5.0
Summary: SDK for Malevich Space
Home-page: https://github.com/MalevichAI/space
License: Apache 2
Author: Zak Davydov
Author-email: zak@malevich.ai
Requires-Python: >=3.10,<3.13
Classifier: License :: Other/Proprietary License
Classifier: Programming Language :: Python :: 3
Classifier: Programming Language :: Python :: 3.10
Classifier: Programming Language :: Python :: 3.11
Classifier: Programming Language :: Python :: 3.12
Requires-Dist: PyYAML (>=6.0,<7.0)
Requires-Dist: aiohttp (>=3.8.5,<4.0.0)
Requires-Dist: gql (>=3.4.0,<4.0.0)
Requires-Dist: pandas (>=2.1.1,<3.0.0)
Requires-Dist: pydantic (>=2.3.0,<3.0.0)
Requires-Dist: rich (>=13.3.2,<14.0.0)
Requires-Dist: tqdm (>=4.66.1,<5.0.0)
Requires-Dist: twine (>=4.0.2,<5.0.0)
Requires-Dist: typer (>=0.7.0)
Requires-Dist: websockets (>=11.0.3,<12.0.0)
Project-URL: Repository, https://github.com/MalevichAI/space
